bibimbap/__init__.py
bibimbap/ganjang.py
bibimbap/gochujang.py
bibimbap-1.0.2.dist-info/METADATA
bibimbap-1.0.2.dist-info/WHEEL
bibimbap-1.0.2.dist-info/top_level.txt
bibimbap-1.0.2.dist-info/RECORD
