Metadata-Version: 2.1
Name: bibimbap
Version: 1.0.2
Summary: selenium based visual automation testing tool
Home-page: https://github.com/sh1223/bibimbap
Author: Seonghwan KIM
Author-email: seonghwankim86@gmail.com
License: UNKNOWN
Platform: UNKNOWN
Classifier: Programming Language :: Python :: 3.7
Requires-Dist: selenium
Requires-Dist: Pillow
